CHANGES.txt
DEPENDENCES.txt
README.txt
setup.py
src/ng/__init__.py
src/ng.adapter.egg-info/PKG-INFO
src/ng.adapter.egg-info/SOURCES.txt
src/ng.adapter.egg-info/dependency_links.txt
src/ng.adapter.egg-info/namespace_packages.txt
src/ng.adapter.egg-info/not-zip-safe
src/ng.adapter.egg-info/requires.txt
src/ng.adapter.egg-info/top_level.txt
src/ng/adapter/__init__.py
src/ng/adapter/configure.zcml
src/ng/adapter/ng.adapter.txt
src/ng/adapter/adaptiveurl/__init__.py
src/ng/adapter/adaptiveurl/adaptiveurl.py
src/ng/adapter/adaptiveurl/configure.zcml
src/ng/adapter/adaptiveurl/interfaces.py
src/ng/adapter/adaptiveurl/browser/__init__.py
src/ng/adapter/adaptiveurl/browser/configure.zcml
src/ng/adapter/breadcrumb/__init__.py
src/ng/adapter/breadcrumb/breadcrumb.txt
src/ng/adapter/breadcrumb/breadcrumbbase.py
src/ng/adapter/breadcrumb/breadcrumbnamespace.py
src/ng/adapter/breadcrumb/configure.zcml
src/ng/adapter/breadcrumb/contained2breadcrumbadapter.py
src/ng/adapter/breadcrumb/interfaces.py
src/ng/adapter/breadcrumb/stop2breadcrumbadapter.py
src/ng/adapter/checksublocation/__init__.py
src/ng/adapter/checksublocation/checksublocation.py
src/ng/adapter/checksublocation/configure.zcml
src/ng/adapter/checksublocation/interfaces.py
src/ng/adapter/checktocontain/__init__.py
src/ng/adapter/checktocontain/checktocontain.py
src/ng/adapter/checktocontain/configure.zcml
src/ng/adapter/etc/ng.adapter-configure.zcml
src/ng/adapter/ianytitle/__init__.py
src/ng/adapter/ianytitle/anytitlesubscriberbase.py
src/ng/adapter/ianytitle/configure.zcml
src/ng/adapter/ianytitle/ianytitle.txt
src/ng/adapter/ianytitle/ianytitleadapter.py
src/ng/adapter/ianytitle/interfaces.py
src/ng/adapter/ianytitle/zdc2titlesubsriber.py
src/ng/adapter/mtime/__init__.py
src/ng/adapter/mtime/configure.zcml
src/ng/adapter/mtime/interfaces.py
src/ng/adapter/mtime/mtimeadapter.py
src/ng/adapter/namechooser/__init__.py
src/ng/adapter/namechooser/configure.zcml
src/ng/adapter/namechooser/interfaces.py
src/ng/adapter/namechooser/namechooser.py
src/ng/adapter/nsinterface/__init__.py
src/ng/adapter/nsinterface/configure.zcml
src/ng/adapter/nsinterface/nsinterface.py
src/ng/adapter/nsinterface/nsinterface.txt
src/ng/adapter/nullsublocations/__init__.py
